po2xls.py
po_excel_translate.py
xls2po.py
po_excel_translate-3.3.dist-info/LICENSE.txt
po_excel_translate-3.3.dist-info/METADATA
po_excel_translate-3.3.dist-info/WHEEL
po_excel_translate-3.3.dist-info/entry_points.txt
po_excel_translate-3.3.dist-info/top_level.txt
po_excel_translate-3.3.dist-info/zip-safe
po_excel_translate-3.3.dist-info/RECORD
