Metadata-Version: 2.1
Name: po-excel-translate
Version: 3.3
Summary: Convert between Excel and PO files
Home-page: https://github.com/NotYetGames/po-excel-translate
Author: Daniel Butum
Author-email: daniel@notyet.eu
License: BSD
Keywords: translation po gettext Babel lingua excel portable object
Platform: UNKNOWN
Classifier: Environment :: Console
Classifier: Intended Audience :: Developers
Classifier: License :: DFSG approved
Classifier: License :: OSI Approved :: BSD License
Classifier: Operating System :: OS Independent
Classifier: Programming Language :: Python :: 3
Classifier: Intended Audience :: Developers
Classifier: Intended Audience :: End Users/Desktop
Requires-Python: >=3.6
Requires-Dist: click
Requires-Dist: polib
Requires-Dist: openpyxl
